domaintools_misp/__init__.py
domaintools_misp/_version.py
domaintools_misp/analyze.py
domaintools_misp/base.py
domaintools_misp/config.py
domaintools_misp/constants.py
domaintools_misp/historic.py
domaintools_misp/iris_detect.py
domaintools_misp/iris_enrich.py
domaintools_misp/iris_import.py
domaintools_misp/iris_investigate.py
domaintools_misp/iris_pivot.py
domaintools_misp/pivot.py
domaintools_misp/install/modules/expansion/DomainTools-Analyze.py
domaintools_misp/install/modules/expansion/DomainTools-Historic.py
domaintools_misp/install/modules/expansion/DomainTools-Iris-Enrich.py
domaintools_misp/install/modules/expansion/DomainTools-Iris-Investigate.py
domaintools_misp/install/modules/expansion/DomainTools-Iris-Pivot.py
domaintools_misp/install/modules/expansion/DomainTools-Pivot.py
domaintools_misp/install/modules/import_mod/DomainTools-Iris-Detect.py
domaintools_misp/install/modules/import_mod/DomainTools-Iris-Import.py
domaintools_misp-0.2.6.dist-info/METADATA
domaintools_misp-0.2.6.dist-info/WHEEL
domaintools_misp-0.2.6.dist-info/top_level.txt
domaintools_misp-0.2.6.dist-info/RECORD
