Metadata-Version: 2.4
Name: domaintools_misp
Version: 0.2.6
Summary: The DomainTools MISP library
Author-email: DomainTools <support@domaintools.com>
Project-URL: Homepage, http://www.domaintools.com/
Project-URL: GitHub, https://github.com/DomainTools/domaintools_misp
Classifier: Programming Language :: Python :: 3
Requires-Python: >=3.7
Requires-Dist: tldextract
Requires-Dist: python-dateutil
Requires-Dist: aiohttp
Requires-Dist: domaintools_api
